scrapy_dotpersistence.py
scrapy_dotpersistence-0.3.0.dist-info/DESCRIPTION.rst
scrapy_dotpersistence-0.3.0.dist-info/METADATA
scrapy_dotpersistence-0.3.0.dist-info/RECORD
scrapy_dotpersistence-0.3.0.dist-info/WHEEL
scrapy_dotpersistence-0.3.0.dist-info/metadata.json
scrapy_dotpersistence-0.3.0.dist-info/top_level.txt
