Metadata-Version: 2.0
Name: scrapy-dotpersistence
Version: 0.3.0
Summary: Scrapy extension to sync `.scrapy` folder to an S3 bucket
Home-page: https://github.com/scrapy-plugins/scrapy-dotpersistence
Author: Scrapy developers
Author-email: opensource@scrapinghub.com
License: BSD
Platform: Any
Classifier: Development Status :: 5 - Production/Stable
Classifier: License :: OSI Approved :: BSD License
Classifier: Operating System :: OS Independent
Classifier: Programming Language :: Python
Classifier: Programming Language :: Python :: 2
Classifier: Programming Language :: Python :: 2.7
Requires-Dist: Scrapy (>=1.0.3)
Requires-Dist: awscli (>=1.10.51)
